[{"nama": "null", "height": 28, "width": 28, "y": 474, "x": 321, "nrp": "null", "color": "#00ff00"}, {"nama": "null", "height": 30, "width": 30, "y": 476, "x": 171, "nrp": "null", "color": "#00ff00"}, {"nama": "null", "height": 39, "width": 39, "y": 486, "x": 363, "nrp": "null", "color": "#00ff00"}, {"nama": "BORIS", "height": 48, "width": 48, "y": 492, "x": 47, "nrp": "1472009", "color": "#00ff00"}, {"nama": "LOTANTO SETIAWAN", "height": 70, "width": 70, "y": 564, "x": 423, "nrp": "1572029", "color": "#00ff00"}]