[{"nama": "REYNARD M. TARUK", "height": 38, "width": 38, "y": 444, "x": 204, "nrp": "1472037", "color": "#00ff00"}, {"nama": "SEHAT ALPRIANTO SITOMPUL", "height": 32, "width": 32, "y": 473, "x": 418, "nrp": "1472080", "color": "#00ff00"}, {"nama": "David Christian Aditya", "height": 47, "width": 47, "y": 492, "x": 239, "nrp": "1472062", "color": "#00ff00"}, {"nama": "HILMAN PEBRIAN PRATAMA", "height": 69, "width": 69, "y": 508, "x": 93, "nrp": "1472071", "color": "#00ff00"}, {"nama": "Rahman", "height": 73, "width": 73, "y": 562, "x": 608, "nrp": "1472056", "color": "#00ff00"}, {"nama": "Bintang Rahadian Prata", "height": 47, "width": 47, "y": 502, "x": 538, "nrp": "1472069", "color": "#00ff00"}]