[
  {
    "name": "Dennis Agustinus",
    "nrp": "1672076",
    "color": "#00ff00",
    "x": 173,
    "y": 343,
    "width": 25,
    "height": 25
  },
  {
    "name": "CHRISTOPHER",
    "nrp": "1672046",
    "color": "#00ff00",
    "x": 104,
    "y": 399,
    "width": 45,
    "height": 45
  },
  {
    "name": "LOUREN FERMANDO",
    "nrp": "1672074",
    "color": "#00ff00",
    "x": 106,
    "y": 353,
    "width": 34,
    "height": 34
  },
  {
    "name": "Christian",
    "nrp": "1672022",
    "color": "#00ff00",
    "x": 296,
    "y": 343,
    "width": 33,
    "height": 33
  },
  {
    "name": "",
    "nrp": "",
    "color": "#00ff00",
    "x": 394,
    "y": 465,
    "width": 73,
    "height": 73
  }
]