[
  {
    "color": "#00ff00",
    "x": 349,
    "y": 455,
    "width": 26,
    "height": 26
  },
  {
    "color": "#00ff00",
    "x": 217,
    "y": 462,
    "width": 25,
    "height": 25
  },
  {
    "color": "#00ff00",
    "x": 368,
    "y": 483,
    "width": 36,
    "height": 36
  },
  {
    "color": "#00ff00",
    "x": 445,
    "y": 512,
    "width": 47,
    "height": 47
  },
  {
    "color": "#00ff00",
    "x": 100,
    "y": 516,
    "width": 53,
    "height": 53
  },
  {
    "color": "#00ff00",
    "x": 160,
    "y": 494,
    "width": 38,
    "height": 38
  }
]