[
  {
    "name": "SHAFIRA PUTRI KURNIAWAN",
    "nrp": "1672040",
    "color": "#00ff00",
    "x": 417,
    "y": 195,
    "width": 22,
    "height": 22
  },
  {
    "name": "NAOMI HELLYNA MAKALEW",
    "nrp": "1672052",
    "color": "#00ff00",
    "x": 519,
    "y": 202,
    "width": 23,
    "height": 23
  },
  {
    "name": "TOMMY",
    "nrp": "1672050",
    "color": "#00ff00",
    "x": 244,
    "y": 210,
    "width": 60,
    "height": 60
  },
  {
    "name": "Steven Christian",
    "nrp": "1672056",
    "color": "#00ff00",
    "x": 327,
    "y": 207,
    "width": 34,
    "height": 34
  },
  {
    "name": "Ardana Putra",
    "nrp": "1572041",
    "color": "#00ff00",
    "x": 938,
    "y": 261,
    "width": 85,
    "height": 85
  },
  {
    "name": "CHRISTIAN CHASTRO",
    "nrp": "1672006",
    "color": "#00ff00",
    "x": 555,
    "y": 232,
    "width": 40,
    "height": 40
  },
  {
    "name": "Alfin Liunardi Senjaya",
    "nrp": "1672034",
    "color": "#00ff00",
    "x": 742,
    "y": 234,
    "width": 49,
    "height": 49
  },
  {
    "name": "Vincent Kho",
    "nrp": "1672071",
    "color": "#00ff00",
    "x": 697,
    "y": 198,
    "width": 45,
    "height": 45
  }
]