[
  {
    "name": "YAFET RAPHAEL",
    "nrp": "1672066",
    "color": "#00ff00",
    "x": 192,
    "y": 435,
    "width": 71,
    "height": 71
  },
  {
    "name": "SHAFIRA PUTRI KURNIAWAN",
    "nrp": "1672040",
    "color": "#00ff00",
    "x": 274,
    "y": 374,
    "width": 38,
    "height": 38
  },
  {
    "name": "NAOMI HELLYNA MAKALEW",
    "nrp": "1672052",
    "color": "#00ff00",
    "x": 362,
    "y": 393,
    "width": 27,
    "height": 27
  },
  {
    "name": "HENRY TIMOTHY HALIM NURADI",
    "nrp": "1672029",
    "color": "#00ff00",
    "x": 466,
    "y": 459,
    "width": 70,
    "height": 70
  }
]