[{"nama": "ANDIKA MULYAWAN DWI PRAPMANTO", "height": 31, "width": 31, "y": 312, "x": 297, "nrp": "1572030", "color": "#00ff00"}, {"nama": "ANANDA DHAMMAHITO ADHE HERLAMBANG", "height": 32, "width": 32, "y": 297, "x": 417, "nrp": "1572002", "color": "#00ff00"}, {"nama": "null", "height": 41, "width": 41, "y": 312, "x": 465, "nrp": "null", "color": "#00ff00"}, {"nama": "Agassi Antonius", "height": 44, "width": 44, "y": 325, "x": 248, "nrp": "1572034", "color": "#00ff00"}, {"nama": "null", "height": 54, "width": 54, "y": 356, "x": 200, "nrp": "null", "color": "#00ff00"}, {"nama": "null", "height": 59, "width": 59, "y": 358, "x": 478, "nrp": "null", "color": "#00ff00"}, {"nama": "null", "height": 99, "width": 99, "y": 396, "x": 55, "nrp": "null", "color": "#00ff00"}, {"nama": "LOTANTO SETIAWAN", "height": 91, "width": 91, "y": 367, "x": 533, "nrp": "1572029", "color": "#00ff00"}]