[
    {
        "color": "#00ff00",
        "x": 82,
        "y": 211,
        "width": 29,
        "height": 29
    },
    {
        "color": "#00ff00",
        "x": 582,
        "y": 245,
        "width": 38,
        "height": 38
    },
    {
        "color": "#00ff00",
        "x": 287,
        "y": 240,
        "width": 45,
        "height": 45
    },
    {
        "color": "#00ff00",
        "x": 731,
        "y": 242,
        "width": 44,
        "height": 44
    },
    {
        "color": "#00ff00",
        "x": 185,
        "y": 254,
        "width": 58,
        "height": 58
    },
    {
        "color": "#00ff00",
        "x": 910,
        "y": 296,
        "width": 64,
        "height": 64
    },
    {
        "color": "#00ff00",
        "x": 791,
        "y": 439,
        "width": 65,
        "height": 65
    }
]