[
  {
    "name": "YOSMART PANGIDOAN BARAKHIEL",
    "nrp": "1772022",
    "color": "#00ff00",
    "x": 373,
    "y": 422,
    "width": 25,
    "height": 25
  },
  {
    "name": "ARIYANTO SANI",
    "nrp": "1772046",
    "color": "#00ff00",
    "x": 175,
    "y": 417,
    "width": 25,
    "height": 25
  },
  {
    "name": "ZALDY IGNATIUS AUW",
    "nrp": "1772031",
    "color": "#00ff00",
    "x": 186,
    "y": 442,
    "width": 31,
    "height": 31
  },
  {
    "name": "TIAZ RIZQY AMANDHA",
    "nrp": "1772052",
    "color": "#00ff00",
    "x": 482,
    "y": 558,
    "width": 72,
    "height": 72
  },
  {
    "name": "CELINE LIESHIANA",
    "nrp": "1772005",
    "color": "#00ff00",
    "x": 68,
    "y": 568,
    "width": 72,
    "height": 72
  },
  {
    "name": "REINALDI GEMILANG SETIAWAN POETRA",
    "nrp": "1772038",
    "color": "#00ff00",
    "x": 380,
    "y": 467,
    "width": 64,
    "height": 64
  },
  {
    "name": "ARIEF KURNIAWAN",
    "nrp": "1772049",
    "color": "#00ff00",
    "x": 322,
    "y": 429,
    "width": 41,
    "height": 41
  }
]