[
    {
        "color": "#00ff00",
        "x": 595,
        "y": 242,
        "width": 26,
        "height": 26
    },
    {
        "color": "#00ff00",
        "x": 289,
        "y": 318,
        "width": 50,
        "height": 50
    },
    {
        "color": "#00ff00",
        "x": 130,
        "y": 259,
        "width": 48,
        "height": 48
    },
    {
        "color": "#00ff00",
        "x": 345,
        "y": 262,
        "width": 48,
        "height": 48
    },
    {
        "color": "#00ff00",
        "x": 655,
        "y": 294,
        "width": 50,
        "height": 50
    },
    {
        "color": "#00ff00",
        "x": 624,
        "y": 273,
        "width": 36,
        "height": 36
    }
]