[
  {
    "color": "#00ff00",
    "x": 465,
    "y": 249,
    "width": 15,
    "height": 15
  },
  {
    "color": "#00ff00",
    "x": 583,
    "y": 242,
    "width": 18,
    "height": 18
  },
  {
    "color": "#00ff00",
    "x": 362,
    "y": 245,
    "width": 18,
    "height": 18
  },
  {
    "color": "#00ff00",
    "x": 605,
    "y": 248,
    "width": 19,
    "height": 19
  },
  {
    "color": "#00ff00",
    "x": 323,
    "y": 257,
    "width": 24,
    "height": 24
  },
  {
    "color": "#00ff00",
    "x": 631,
    "y": 258,
    "width": 22,
    "height": 22
  },
  {
    "color": "#00ff00",
    "x": 359,
    "y": 272,
    "width": 24,
    "height": 24
  },
  {
    "color": "#00ff00",
    "x": 470,
    "y": 275,
    "width": 27,
    "height": 27
  },
  {
    "color": "#00ff00",
    "x": 499,
    "y": 289,
    "width": 30,
    "height": 30
  },
  {
    "color": "#00ff00",
    "x": 508,
    "y": 251,
    "width": 21,
    "height": 21
  },
  {
    "color": "#00ff00",
    "x": 675,
    "y": 270,
    "width": 32,
    "height": 32
  },
  {
    "color": "#00ff00",
    "x": 300,
    "y": 305,
    "width": 33,
    "height": 33
  },
  {
    "color": "#00ff00",
    "x": 870,
    "y": 301,
    "width": 45,
    "height": 45
  },
  {
    "color": "#00ff00",
    "x": 222,
    "y": 315,
    "width": 48,
    "height": 48
  },
  {
    "color": "#00ff00",
    "x": 557,
    "y": 328,
    "width": 48,
    "height": 48
  },
  {
    "color": "#00ff00",
    "x": 29,
    "y": 288,
    "width": 27,
    "height": 27
  }
]