[
  {
    "name": "MULYADI DHARMAWAN",
    "nrp": "1772028",
    "color": "#00ff00",
    "x": 385,
    "y": 496,
    "width": 20,
    "height": 20
  },
  {
    "name": "KELVIN",
    "nrp": "1772014",
    "color": "#00ff00",
    "x": 222,
    "y": 533,
    "width": 47,
    "height": 47
  },
  {
    "name": "ANASTASIA LEVINA",
    "nrp": "1772020",
    "color": "#00ff00",
    "x": 363,
    "y": 522,
    "width": 27,
    "height": 27
  },
  {
    "name": "CELINE LIESHIANA",
    "nrp": "1772005",
    "color": "#00ff00",
    "x": 186,
    "y": 525,
    "width": 25,
    "height": 25
  },
  {
    "name": "ZALDY IGNATIUS AUW",
    "nrp": "1772031",
    "color": "#00ff00",
    "x": 214,
    "y": 493,
    "width": 33,
    "height": 33
  },
  {
    "name": "TIAZ RIZQY AMANDHA",
    "nrp": "1772052",
    "color": "#00ff00",
    "x": 322,
    "y": 619,
    "width": 50,
    "height": 50
  },
  {
    "name": "NATASYA DEY",
    "nrp": "1772041",
    "color": "#00ff00",
    "x": 411,
    "y": 537,
    "width": 44,
    "height": 44
  },
  {
    "name": "FEBRINA ANASTASHA",
    "nrp": "1772006",
    "color": "#00ff00",
    "x": 146,
    "y": 621,
    "width": 53,
    "height": 53
  }
]